r2io.py
r2io-0.1.5.dist-info/WHEEL
r2io-0.1.5.dist-info/METADATA
r2io-0.1.5.dist-info/RECORD
