Metadata-Version: 2.1
Name: r2io
Version: 0.1.5
Summary: Decoding [seismic] r2 files using python.
License: MIT
Author: Jordan Dennis
Author-email: jdenn105@gmail.com
Requires-Python: >=3.8,<4.0
Classifier: License :: OSI Approved :: MIT License
Classifier: Programming Language :: Python :: 3
Classifier: Programming Language :: Python :: 3.10
Classifier: Programming Language :: Python :: 3.8
Classifier: Programming Language :: Python :: 3.9
Requires-Dist: numpy (>=1.0,<2.0)
